pydantic_async_validation/__init__.py
pydantic_async_validation/constants.py
pydantic_async_validation/fastapi.py
pydantic_async_validation/metaclasses.py
pydantic_async_validation/mixins.py
pydantic_async_validation/py.typed
pydantic_async_validation/utils.py
pydantic_async_validation/validators.py
pydantic_async_validation-0.4.1.dist-info/licenses/LICENSE
pydantic_async_validation-0.4.1.dist-info/WHEEL
pydantic_async_validation-0.4.1.dist-info/METADATA
pydantic_async_validation-0.4.1.dist-info/RECORD
