Metadata-Version: 2.4
Name: pydantic-async-validation
Version: 0.4.1
Summary: Add async validation to pydantic
Author: TEAM23 GmbH
Author-email: TEAM23 GmbH <info@team23.de>
License-Expression: MIT
License-File: LICENSE
Requires-Dist: pydantic>=2.0.0,<3.0.0
Requires-Dist: fastapi>=0.100.0,<1.0.0 ; extra == 'fastapi'
Requires-Python: >=3.10
Project-URL: Repository, https://github.com/team23/pydantic-async-validation
Provides-Extra: fastapi
